MANIFEST.in
README.txt
requirements.txt
setup.py
MultiAug.egg-info/PKG-INFO
MultiAug.egg-info/SOURCES.txt
MultiAug.egg-info/dependency_links.txt
MultiAug.egg-info/top_level.txt
docs/build/html/_sources/index.rst.txt
docs/build/html/_sources/modules.rst.txt
docs/build/html/_sources/multiaug.augmenters.image3d.rst.txt
docs/build/html/_sources/multiaug.augmenters.rst.txt
docs/build/html/_sources/multiaug.augmenters.tabular.rst.txt
docs/build/html/_sources/multiaug.rst.txt
docs/build/html/_sources/multiaug.test.rst.txt
multiaug/__init__.py
multiaug/augmenters/__init__.py
multiaug/augmenters/meta.py
multiaug/augmenters/image3d/__init__.py
multiaug/augmenters/image3d/rotate.py
multiaug/augmenters/tabular/__init__.py
multiaug/augmenters/tabular/gaussian_perturbation.py
multiaug/test/__init__.py
multiaug/test/test_gaussian_perturbation.py
multiaug/test/test_integration.py
multiaug/test/test_meta.py
multiaug/test/test_rotate_image3d.py